{
  "Misha_Awan": {
    "first_name": "Ngina",
    "last_name": "Awan",
    "username": "Misha_Awan",
    "email": "mawan@macalester.edu",
    "password_hash": "scrypt:32768:8:1$d8T5XDbWXF2e91UV$ed9af3dc561bb10cf60c9f9d58e502ae2f668ba53dcff8f2bd72883b4696b2a028340f178014e24cbdd67c41a4501577615830cc8247a6176fd1669f035c0fbc",
    "gender": "Male",
    "dob": "2006-02-02",
    "hometown": "Bor (Jonglei)",
    "bio": "Bio",
    "category": "Musician",
    "geez": [],
    "pending_sent": [],
    "posts": [],
    "photo_permission": true
  },
  "nyla": {
    "first_name": "Nyla",
    "last_name": "Deng",
    "username": "nyla",
    "email": "nyla@x.com",
    "password_hash": "scrypt:32768:8:1$C3AGpyZn9FZd8BRu$108e10a4fc1562b12d52a57c879d089bbca6b3428f2f9e925155e18bc2f126c1b07e7635543361fc741cc8d923541890220c89bd44103e9a4b30c350667a3ddb",
    "gender": "Female",
    "dob": "1998-03-03",
    "hometown": "Rumbek",
    "bio": "word word word word word word word word word word word word word word word word word word word word word word word word word word word word word word word word word word word word word word word word word word word word word word word word word word word word word word word word word word word word word word word word word word word word word word word word word word word word word word word word word word word word word word word word word word word word word word word word word word word word word word word word word",
    "category": "Student",
    "geez": [],
    "pending_sent": [],
    "posts": [],
    "photo_permission": false
  }
}